setup.py
distributions_davidtest/Binomialdistribution.py
distributions_davidtest/Gaussiandistribution.py
distributions_davidtest/Generaldistribution.py
distributions_davidtest/__init__.py
distributions_davidtest.egg-info/PKG-INFO
distributions_davidtest.egg-info/SOURCES.txt
distributions_davidtest.egg-info/dependency_links.txt
distributions_davidtest.egg-info/not-zip-safe
distributions_davidtest.egg-info/top_level.txt